access_control/__init__.py
access_control/acl.py
access_control/context.py
access_control/permission.py
access_control/permit.py
access_control/principal.py
access_control-0.3.0.dist-info/WHEEL
access_control-0.3.0.dist-info/METADATA
access_control-0.3.0.dist-info/RECORD
