Metadata-Version: 2.1
Name: access-control
Version: 0.3.0
Summary: Library for access control lists
Home-page: https://github.com/mrijken/access_control
License: MIT
Author: Marc Rijken
Author-email: marc@rijken.org
Requires-Python: >=3.6,<4.0
Classifier: License :: OSI Approved :: MIT License
Classifier: Programming Language :: Python :: 3
Classifier: Programming Language :: Python :: 3.6
Classifier: Programming Language :: Python :: 3.7
Classifier: Programming Language :: Python :: 3.8
Classifier: Programming Language :: Python :: 3.9
Requires-Dist: subscribe (>=0.5.0)
Project-URL: Repository, https://github.com/mrijken/access_control
